dash_tooltip/__init__.py
dash_tooltip/_version.py
dash_tooltip/config.py
dash_tooltip/custom_figure.py
dash_tooltip/utils.py
dash_tooltip-0.4.2.dist-info/LICENSE
dash_tooltip-0.4.2.dist-info/METADATA
dash_tooltip-0.4.2.dist-info/WHEEL
dash_tooltip-0.4.2.dist-info/top_level.txt
dash_tooltip-0.4.2.dist-info/RECORD
