Metadata-Version: 2.2
Name: Dash_tooltip
Version: 0.4.2
Summary: A tooltip functionality for Dash.
Author: kb-
Project-URL: Homepage, https://github.com/kb-/Dash_tooltip
Classifier: Programming Language :: Python :: 3
Classifier: Programming Language :: Python :: 3.7
Classifier: Programming Language :: Python :: 3.8
Classifier: Programming Language :: Python :: 3.9
Classifier: Programming Language :: Python :: 3.10
Classifier: Programming Language :: Python :: 3.11
Classifier: Programming Language :: Python :: 3.12
Classifier: Programming Language :: Python :: 3.13
Classifier: License :: OSI Approved :: MIT License
Classifier: Operating System :: OS Independent
Requires-Python: >=3.7
License-File: LICENSE
Requires-Dist: dash>=2.13.0
Requires-Dist: plotly>=5.17.0
